pysbolgraph/CompliantURIs.py
pysbolgraph/S2Attachment.py
pysbolgraph/S2Component.py
pysbolgraph/S2Cut.py
pysbolgraph/S2Experiment.py
pysbolgraph/S2ExperimentalData.py
pysbolgraph/S2FunctionalComponent.py
pysbolgraph/S2GenericLocation.py
pysbolgraph/S2Identified.py
pysbolgraph/S2IdentifiedFactory.py
pysbolgraph/S2Interaction.py
pysbolgraph/S2Location.py
pysbolgraph/S2MapsTo.py
pysbolgraph/S2Measure.py
pysbolgraph/S2Model.py
pysbolgraph/S2Module.py
pysbolgraph/S2Participation.py
pysbolgraph/S2ProvActivity.py
pysbolgraph/S2ProvAgent.py
pysbolgraph/S2ProvAssociation.py
pysbolgraph/S2ProvPlan.py
pysbolgraph/S2ProvUsage.py
pysbolgraph/S2Range.py
pysbolgraph/S2Sequence.py
pysbolgraph/S2SequenceAnnotation.py
pysbolgraph/S2SequenceConstraint.py
pysbolgraph/SBOL2Graph.py
pysbolgraph/SBOL2Serialize.py
pysbolgraph/SBOL2Validate.py
pysbolgraph/__init__.py
pysbolgraph/terms.py
pysbolgraph-0.2.0.dist-info/DESCRIPTION.rst
pysbolgraph-0.2.0.dist-info/METADATA
pysbolgraph-0.2.0.dist-info/RECORD
pysbolgraph-0.2.0.dist-info/WHEEL
pysbolgraph-0.2.0.dist-info/metadata.json
pysbolgraph-0.2.0.dist-info/top_level.txt
