Metadata-Version: 2.0
Name: pysbolgraph
Version: 0.2.0
Summary: A simple Python library to read and write SBOL files
Home-page: https://github.com/udp/pysbolgraph
Author: James Alastair McLaughlin
Author-email: james@mclgh.net
License: UNKNOWN
Platform: UNKNOWN
Classifier: Programming Language :: Python :: 3
Classifier: Programming Language :: Python :: 2
Classifier: License :: OSI Approved :: BSD License
Classifier: Operating System :: OS Independent
Requires-Dist: lxml
Requires-Dist: rdflib
Requires-Dist: requests
